README.md
setup.py
pytraits.egg-info/PKG-INFO
pytraits.egg-info/SOURCES.txt
pytraits.egg-info/dependency_links.txt
pytraits.egg-info/entry_points.txt
pytraits.egg-info/requires.txt
pytraits.egg-info/top_level.txt
traits/__init__.py
traits/apply.py
traits/helpers.py