Metadata-Version: 2.1
Name: pytraits
Version: 0.0.1
Summary: apply traits to your YAML template
Home-page: https://github.com/TaylorHere/traits
Author: TaylorHere
Author-email: taylorherelee@gmail.com
License: UNKNOWN
Platform: UNKNOWN
Classifier: Programming Language :: Python :: 3
Classifier: License :: OSI Approved :: MIT License
